{
    "time":"2022/5/20 11:00\n~\n2022/5/30 10:59",
    "chara_pool_title":"3★目白善信Pickup卡池",
    "chara_pool_img":"https://patchwiki.biligame.com/images/umamusume/0/00/r63dcgg3vydcfpsweqg54njqcv7p5ol.png",
    "chara_name":[
        "目白善信"
    ],
    "chara_id":[
        "106401"
    ],
    "card_pool_title":"SSR待兼福来、SSR米浴 Pickup卡池",
    "card_pool_img":"https://patchwiki.biligame.com/images/umamusume/1/10/q93ocm5toam2ki0y2sn0ngcfvkcd094.png",
    "card_name":[
        "【袖振り合えば福となる♪】マチカネフクキタル",
        "【幸せは曲がり角の向こう】ライスシャワー"
    ],
    "card_img_altt":[
        "Support_thumb_30078.png",
        "Support_thumb_30034.png"
    ]
}